turbob64-1.1.1.data/platlib/_build.py
turbob64-1.1.1.data/platlib/turbob64.cp311-win_amd64.pyd
turbob64-1.1.1.dist-info/LICENSE
turbob64-1.1.1.dist-info/METADATA
turbob64-1.1.1.dist-info/WHEEL
turbob64-1.1.1.dist-info/top_level.txt
turbob64-1.1.1.dist-info/RECORD
