Metadata-Version: 2.1
Name: turbob64
Version: 1.1.1
Summary: Cython bindings for Turbo Base64
Author-email: daijro <daijro.dev@gmail.com>
License: GPL-3.0
Project-URL: repository, https://github.com/daijro/turbobase64
Keywords: base64,encoding,decoding,turbo,cython
Classifier: Programming Language :: Python :: 3
Classifier: Programming Language :: C
Requires-Python: >=3.7
License-File: LICENSE
